COPYRIGHT
DIST
LICENSE
MANIFEST.in
ez_setup.py
setup.py
bin/modipy
doc/modipy-config.dtd
etc/add_vfiler.xml
etc/netapp-create-volume.change-template.xml
etc/netapp-provision-demo.xml
etc/netapp-provision-zapi-demo.xml
etc/templating.xml
etc/test-netapp-templates.xml
etc/test_change.xml
etc/test_iterator.csv
examples/hello-change.xml
examples/netapp-provision-demo.xml
lib/ModiPy.egg-info/PKG-INFO
lib/ModiPy.egg-info/SOURCES.txt
lib/ModiPy.egg-info/dependency_links.txt
lib/ModiPy.egg-info/top_level.txt
lib/modipy/__init__.py
lib/modipy/base.py
lib/modipy/change.py
lib/modipy/change_command.py
lib/modipy/confloader.py
lib/modipy/debug.py
lib/modipy/device.py
lib/modipy/interfaces.py
lib/modipy/iterator.py
lib/modipy/namespace.py
lib/modipy/netapp.py
lib/modipy/object.py
lib/modipy/options.py
lib/modipy/provisioner.py
lib/modipy/provisioner_command.py
lib/modipy/provisioner_ssh.py
lib/modipy/sshsimpleclient.py
lib/modipy/util.py
templates/netapp-create-qtree.change-template.xml
templates/netapp-create-qtree.zapi.change-template.xml
templates/netapp-create-volume.change-template.xml
templates/netapp-create-volume.zapi.change-template.xml
templates/netapp-destroy-volume.change-template.xml
templates/netapp-destroy-volume.zapi.change-template.xml
templates/netapp-getfile.zapi.change-template.xml
templates/netapp-list-qtrees.zapi.xml
templates/netapp-putfile.zapi.change-template.xml
templates/netapp-set-qtree-security.change-template.xml
templates/netapp-set-qtree-security.zapi.change-template.xml
templates/netapp-set-volume-option.change-template.xml
templates/netapp-set-volume-option.zapi.change-template.xml
test/__init__.py
test/change.netapp.getfileputfile.xml
test/change_stub.py
test/device_stub.py
test/test_change.py
test/test_change_flows.py
test/test_expectproto.py
test/test_iterator.py
test/test_netapp.py
test/test_parsing.py
test/test_provisioner.py
test/test_provisioner_command.py
test/test_ssh.py
test/test_configs/iterator.csv
test/test_configs/multiple_expects.xml
test/test_configs/post_prereqs.xml
test/test_configs/prereq_inside_change.xml