Metadata-Version: 1.0
Name: ModiPy
Version: 1.2.2
Summary: ModiPy change management system
Home-page: http://modipy.seafelt.com
Author: Justin Warren
Author-email: daedalus@eigenmagic.com
License: LGPL
Download-URL: http://www.seafelt.com/software/sources
Keywords: change automation
Platform: UNKNOWN
Classifier: Development Status :: 4 - Beta
Classifier: Environment :: Console
Classifier: Intended Audience :: System Administrators
Classifier: Intended Audience :: Developers
Classifier: Intended Audience :: Information Technology
Classifier: License :: OSI Approved :: GNU Library or Lesser General Public License (LGPL)
Classifier: Natural Language :: English
Classifier: Operating System :: POSIX
Classifier: Programming Language :: Python
Classifier: Topic :: Office/Business :: Scheduling
Classifier: Topic :: System :: Installation/Setup
Classifier: Topic :: System :: Systems Administration
Classifier: Topic :: Utilities
